pyspecter/CommonObservables.py
pyspecter/Observables.py
pyspecter/SPECTER.py
pyspecter/SpectralEMD_Helper.py
pyspecter/__init__.py
pyspecter/_version.py
pyspecter/cpp/find_pairs
pyspecter/cpp/find_pairs.c
pyspecter/cpp/find_pairs.h
pyspecter/cpp/find_pairs.pyx
pyspecter/cpp/setup.py
pyspecter/cython/find_indices_cython.c
pyspecter/cython/find_indices_cython.pyx
pyspecter/cython/find_pairs
pyspecter/cython/find_pairs.c
pyspecter/cython/setup.py
pyspecter/cython/test copy.ipynb
pyspecter/cython/test.ipynb
pyspecter/utils/__init__.py
pyspecter/utils/data_utils.py
pyspecter/utils/plot_utils.py
specterpy-1.1.0.dist-info/METADATA
specterpy-1.1.0.dist-info/WHEEL
specterpy-1.1.0.dist-info/licenses/LICENSE
specterpy-1.1.0.dist-info/RECORD
