Metadata-Version: 2.4
Name: specterpy
Version: 1.1.0
Summary: framework for defining, building, and evaluating generalized shape observables for collider physics
Project-URL: Documentation, https://github.com/rikab/SPECTER
Project-URL: Homepage, https://github.com/rikab/SPECTER
Project-URL: Issue Tracker, https://github.com/rikab/SPECTER/issues
Project-URL: Releases, https://github.com/rikab/SPECTER/releases
Project-URL: Source Code, https://github.com/rikab/SPECTER
Author-email: Rikab Gambhir <rikab@mit.edu>
License: MIT
License-File: LICENSE
Keywords: jet physics,shape observables
Classifier: Development Status :: 3 - Alpha
Classifier: Intended Audience :: Science/Research
Classifier: License :: OSI Approved :: MIT License
Classifier: Programming Language :: Python :: 3
Classifier: Programming Language :: Python :: 3 :: Only
Classifier: Programming Language :: Python :: 3.7
Classifier: Programming Language :: Python :: 3.8
Classifier: Programming Language :: Python :: 3.9
Classifier: Programming Language :: Python :: 3.10
Classifier: Programming Language :: Python :: Implementation :: CPython
Classifier: Topic :: Scientific/Engineering
Classifier: Topic :: Scientific/Engineering :: Physics
Requires-Python: >=3.7
Requires-Dist: jax>=0.4.13
Requires-Dist: jaxlib>=0.4.13
Requires-Dist: matplotlib>=3.5.0
Requires-Dist: numpy
Requires-Dist: particleloader
Requires-Dist: rikabplotlib
Requires-Dist: scipy>=1.5.1
